Workbook

Sheet Данные
A1: Sku | B1: Категория | C1: Бренд | D1: Товар | E1: Цена. ₽ | F1: Себест., ₽ | G1: Продажи/мес | H1: Выручка ₽ | I1: Маржа ₽ | J1: Маржа % | K1: Запасы шт | L1: Янв | M1: Фев | N1: Март | O1: Апрель
A2: ="SKU"&TEXT(ROW(A1),"000") -> SKU001 | B2: Холодильники | C2: Samsung | D2: Холодильник F | E2: 30000 | F2: 22000 | G2: 120 | H2: =E2*G2 -> 3600000 | I2: =(E2-F2)*G2 -> 960000 | J2: =IF(H2>0,(E2-F2)/E2,0) -> 0.26666667 | K2: 20 | L2: 115 | M2: 122 | N2: 118 | O2: 125
A3: ="SKU"&TEXT(ROW(A2),"000") -> SKU002 | B3: Холодильники | C3: LG | D3: Холодильник B | E3: 35000 | F3: 28000 | G3: 60 | H3: =E3*G3 -> 2100000 | I3: =(E3-F3)*G3 -> 420000 | J3: =IF(H3>0,(E3-F3)/E3,0) -> 0.2 | K3: 30 | L3: 55 | M3: 68 | N3: 52 | O3: 70
A4: ="SKU"&TEXT(ROW(A3),"000") -> SKU003 | B4: Стиралки | C4: Bosch | D4: Стиралка C | E4: 45000 | F4: 35000 | G4: 80 | H4: =E4*G4 -> 3600000 | I4: =(E4-F4)*G4 -> 800000 | J4: =IF(H4>0,(E4-F4)/E4,0) -> 0.22222222 | K4: 10 | L4: 78 | M4: 85 | N4: 72 | O4: 88
A5: ="SKU"&TEXT(ROW(A4),"000") -> SKU004 | B5: Микроволновки | C5: Samsung | D5: Микра D | E5: 8000 | F5: 5500 | G5: 150 | H5: =E5*G5 -> 1200000 | I5: =(E5-F5)*G5 -> 375000 | J5: =IF(H5>0,(E5-F5)/E5,0) -> 0.3125 | K5: 50 | L5: 145 | M5: 155 | N5: 140 | O5: 160
A6: ="SKU"&TEXT(ROW(A5),"000") -> SKU005 | B6: Чайники Tefal | C6: E Premium | D6: Чайник E | E6: 2500 | F6: 1800 | G6: 300 | H6: =E6*G6 -> 750000 | I6: =(E6-F6)*G6 -> 210000 | J6: =IF(H6>0,(E6-F6)/E6,0) -> 0.28 | K6: 200 | L6: 290 | M6: 310 | N6: 285 | O6: 320
A7: ="SKU"&TEXT(ROW(A6),"000") -> SKU006 | B7: Чайники Philips | C7: F Compact | D7: Чайник F | E7: 2000 | F7: 1600 | G7: 50 | H7: =E7*G7 -> 100000 | I7: =(E7-F7)*G7 -> 20000 | J7: =IF(H7>0,(E7-F7)/E7,0) -> 0.2 | K7: 40 | L7: 40 | M7: 65 | N7: 35 | O7: 70
A8: ="SKU"&TEXT(ROW(A7),"000") -> SKU007 | B8: Холодильники | C8: Haier | D8: Холод Pro | E8: 55000 | F8: 42000 | G8: 25 | H8: =E8*G8 -> 1375000 | I8: =(E8-F8)*G8 -> 325000 | J8: =IF(H8>0,(E8-F8)/E8,0) -> 0.23636364 | K8: 8 | L8: 22 | M8: 28 | N8: 24 | O8: 30
A9: ="SKU"&TEXT(ROW(A8),"000") -> SKU008 | B9: Стиралки | C9: LG | D9: Стиралка Slim | E9: 32000 | F9: 24000 | G9: 45 | H9: =E9*G9 -> 1440000 | I9: =(E9-F9)*G9 -> 360000 | J9: =IF(H9>0,(E9-F9)/E9,0) -> 0.25 | K9: 15 | L9: 42 | M9: 48 | N9: 49 | O9: 52
A10: ="SKU"&TEXT(ROW(A9),"000") -> SKU009 | B10: Микроволновки | C10: LG | D10: Микра Smart | E10: 12000 | F10: 8500 | G10: 65 | H10: =E10*G10 -> 780000 | I10: =(E10-F10)*G10 -> 227500 | J10: =IF(H10>0,(E10-F10)/E10,0) -> 0.29166667 | K10: 22 | L10: 60 | M10: 72 | N10: 57 | O10: 75
A11: ="SKU"&TEXT(ROW(A10),"000") -> SKU010 | B11: Холодильники | C11: Samsung | D11: Чайник Styline | E11: 3200 | F11: 2400 | G11: 85 | H11: =E11*G11 -> 272000 | I11: =(E11-F11)*G11 -> 68000 | J11: =IF(H11>0,(E11-F11)/E11,0) -> 0.25 | K11: 65 | L11: 80 | M11: 90 | N11: 82 | O11: 95

Sheet ABC
A1: Ранг | B1: Sku | C1: Товар | D1: Категория | E1: Выручка ₽ | F1: Доля % | G1: Кумулятив % | H1: Группа ABC
A2: =ROW()-1 -> 1 | B2: =INDEX(Данные[Sku], A2) -> SKU001 | C2: =Данные[Товар] -> Холодильник F | D2: =Данные[Категория] -> Холодильники | E2: =Данные[Выручка ₽] -> 3600000 | F2: =E2/SUM($E$2:$E$11) -> 0.23657751 | G2: =SUM($F$2:F2) -> 0.23657751 | H2: =IF(G2<=0.8,"A",IF(G2<=0.95,"B","C")) -> A
A3: =ROW()-1 -> 2 | B3: =INDEX(Данные[Sku], A3) -> SKU002 | C3: =Данные[Товар] -> Холодильник B | D3: =Данные[Категория] -> Холодильники | E3: =Данные[Выручка ₽] -> 2100000 | F3: =E3/SUM($E$2:$E$11) -> 0.13800355 | G3: =SUM($F$2:F3) -> 0.37458106 | H3: =IF(G3<=0.8,"A",IF(G3<=0.95,"B","C")) -> A
A4: =ROW()-1 -> 3 | B4: =INDEX(Данные[Sku], A4) -> SKU003 | C4: =Данные[Товар] -> Стиралка C | D4: =Данные[Категория] -> Стиралки | E4: =Данные[Выручка ₽] -> 3600000 | F4: =E4/SUM($E$2:$E$11) -> 0.23657751 | G4: =SUM($F$2:F4) -> 0.61115857 | H4: =IF(G4<=0.8,"A",IF(G4<=0.95,"B","C")) -> A
A5: =ROW()-1 -> 4 | B5: =INDEX(Данные[Sku], A5) -> SKU004 | C5: =Данные[Товар] -> Микра D | D5: =Данные[Категория] -> Микроволновки | E5: =Данные[Выручка ₽] -> 1200000 | F5: =E5/SUM($E$2:$E$11) -> 0.078859171 | G5: =SUM($F$2:F5) -> 0.69001774 | H5: =IF(G5<=0.8,"A",IF(G5<=0.95,"B","C")) -> A
A6: =ROW()-1 -> 5 | B6: =INDEX(Данные[Sku], A6) -> SKU005 | C6: =Данные[Товар] -> Чайник E | D6: =Данные[Категория] -> Чайники Tefal | E6: =Данные[Выручка ₽] -> 750000 | F6: =E6/SUM($E$2:$E$11) -> 0.049286982 | G6: =SUM($F$2:F6) -> 0.73930472 | H6: =IF(G6<=0.8,"A",IF(G6<=0.95,"B","C")) -> A
A7: =ROW()-1 -> 6 | B7: =INDEX(Данные[Sku], A7) -> SKU006 | C7: =Данные[Товар] -> Чайник F | D7: =Данные[Категория] -> Чайники Philips | E7: =Данные[Выручка ₽] -> 100000 | F7: =E7/SUM($E$2:$E$11) -> 0.0065715976 | G7: =SUM($F$2:F7) -> 0.74587632 | H7: =IF(G7<=0.8,"A",IF(G7<=0.95,"B","C")) -> A
A8: =ROW()-1 -> 7 | B8: =INDEX(Данные[Sku], A8) -> SKU007 | C8: =Данные[Товар] -> Холод Pro | D8: =Данные[Категория] -> Холодильники | E8: =Данные[Выручка ₽] -> 1375000 | F8: =E8/SUM($E$2:$E$11) -> 0.090359466 | G8: =SUM($F$2:F8) -> 0.83623579 | H8: =IF(G8<=0.8,"A",IF(G8<=0.95,"B","C")) -> B
A9: =ROW()-1 -> 8 | B9: =INDEX(Данные[Sku], A9) -> SKU008 | C9: =Данные[Товар] -> Стиралка Slim | D9: =Данные[Категория] -> Стиралки | E9: =Данные[Выручка ₽] -> 1440000 | F9: =E9/SUM($E$2:$E$11) -> 0.094631005 | G9: =SUM($F$2:F9) -> 0.93086679 | H9: =IF(G9<=0.8,"A",IF(G9<=0.95,"B","C")) -> B
A10: =ROW()-1 -> 9 | B10: =INDEX(Данные[Sku], A10) -> SKU009 | C10: =Данные[Товар] -> Микра Smart | D10: =Данные[Категория] -> Микроволновки | E10: =Данные[Выручка ₽] -> 780000 | F10: =E10/SUM($E$2:$E$11) -> 0.051258461 | G10: =SUM($F$2:F10) -> 0.98212525 | H10: =IF(G10<=0.8,"A",IF(G10<=0.95,"B","C")) -> C
A11: =ROW()-1 -> 10 | B11: =INDEX(Данные[Sku], A11) -> SKU010 | C11: =Данные[Товар] -> Чайник Styline | D11: =Данные[Категория] -> Холодильники | E11: =Данные[Выручка ₽] -> 272000 | F11: =E11/SUM($E$2:$E$11) -> 0.017874745 | G11: =SUM($F$2:F11) -> 1 | H11: =IF(G11<=0.8,"A",IF(G11<=0.95,"B","C")) -> C

Sheet XYZ
A1: Sku | B1: Товар | C1: Среднее продаж | D1: Станд. Отклонение | E1: CV % | F1: Группа XYZ | G1: Интерпретация
A2: =Данные[Sku] -> SKU001 | B2: =Данные[Товар] -> Холодильник F | C2: =AVERAGE(Данные!L2:O2) -> 120 | D2: =_xlfn.STDEV.S( VLOOKUP($A2,Данные!$A$2:$O$11,12,0), VLOOKUP($A2,Данные!$A$2:$O$11,13,0), VLOOKUP($A2,Данные!$A$2:$O$11,14,0), VLOOKUP($A2,Данные!$A$2:$O$11,15,0) ) -> 4.3969687 | E2: =IF(C2=0,0,(D2/C2*100)) -> 3.6641405 | F2: =IF(E2<=10,"X",IF(E2<=25,"Y","Z")) -> X | G2: =IF(F2="X","✅ Стабильный спрос - точный прогноз", IF(F2="Y","⚠️ Умеренные колебания - корректировать заказ", "❌ Нестабильность - под заказ")) -> ✅ Стабильный спрос - точный прогноз
A3: =Данные[Sku] -> SKU002 | B3: =Данные[Товар] -> Холодильник B | C3: =AVERAGE(Данные!L3:O3) -> 61.25 | D3: =_xlfn.STDEV.S( VLOOKUP($A3,Данные!$A$2:$O$11,12,0), VLOOKUP($A3,Данные!$A$2:$O$11,13,0), VLOOKUP($A3,Данные!$A$2:$O$11,14,0), VLOOKUP($A3,Данные!$A$2:$O$11,15,0) ) -> 9.0691786 | E3: =IF(C3=0,0,(D3/C3*100)) -> 14.806822 | F3: =IF(E3<=10,"X",IF(E3<=25,"Y","Z")) -> Y | G3: =IF(F3="X","✅ Стабильный спрос - точный прогноз", IF(F3="Y","⚠️ Умеренные колебания - корректировать заказ", "❌ Нестабильность - под заказ")) -> ⚠️ Умеренные колебания - корректировать заказ
A4: =Данные[Sku] -> SKU003 | B4: =Данные[Товар] -> Стиралка C | C4: =AVERAGE(Данные!L4:O4) -> 80.75 | D4: =_xlfn.STDEV.S( VLOOKUP($A4,Данные!$A$2:$O$11,12,0), VLOOKUP($A4,Данные!$A$2:$O$11,13,0), VLOOKUP($A4,Данные!$A$2:$O$11,14,0), VLOOKUP($A4,Данные!$A$2:$O$11,15,0) ) -> 7.1821538 | E4: =IF(C4=0,0,(D4/C4*100)) -> 8.8943081 | F4: =IF(E4<=10,"X",IF(E4<=25,"Y","Z")) -> X | G4: =IF(F4="X","✅ Стабильный спрос - точный прогноз", IF(F4="Y","⚠️ Умеренные колебания - корректировать заказ", "❌ Нестабильность - под заказ")) -> ✅ Стабильный спрос - точный прогноз
A5: =Данные[Sku] -> SKU004 | B5: =Данные[Товар] -> Микра D | C5: =AVERAGE(Данные!L5:O5) -> 150 | D5: =_xlfn.STDEV.S( VLOOKUP($A5,Данные!$A$2:$O$11,12,0), VLOOKUP($A5,Данные!$A$2:$O$11,13,0), VLOOKUP($A5,Данные!$A$2:$O$11,14,0), VLOOKUP($A5,Данные!$A$2:$O$11,15,0) ) -> 9.1287093 | E5: =IF(C5=0,0,(D5/C5*100)) -> 6.0858062 | F5: =IF(E5<=10,"X",IF(E5<=25,"Y","Z")) -> X | G5: =IF(F5="X","✅ Стабильный спрос - точный прогноз", IF(F5="Y","⚠️ Умеренные колебания - корректировать заказ", "❌ Нестабильность - под заказ")) -> ✅ Стабильный спрос - точный прогноз
A6: =Данные[Sku] -> SKU005 | B6: =Данные[Товар] -> Чайник E | C6: =AVERAGE(Данные!L6:O6) -> 301.25 | D6: =_xlfn.STDEV.S( VLOOKUP($A6,Данные!$A$2:$O$11,12,0), VLOOKUP($A6,Данные!$A$2:$O$11,13,0), VLOOKUP($A6,Данные!$A$2:$O$11,14,0), VLOOKUP($A6,Данные!$A$2:$O$11,15,0) ) -> 16.52019 | E6: =IF(C6=0,0,(D6/C6*100)) -> 5.4838804 | F6: =IF(E6<=10,"X",IF(E6<=25,"Y","Z")) -> X | G6: =IF(F6="X","✅ Стабильный спрос - точный прогноз", IF(F6="Y","⚠️ Умеренные колебания - корректировать заказ", "❌ Нестабильность - под заказ")) -> ✅ Стабильный спрос - точный прогноз
A7: =Данные[Sku] -> SKU006 | B7: =Данные[Товар] -> Чайник F | C7: =AVERAGE(Данные!L7:O7) -> 52.5 | D7: =_xlfn.STDEV.S( VLOOKUP($A7,Данные!$A$2:$O$11,12,0), VLOOKUP($A7,Данные!$A$2:$O$11,13,0), VLOOKUP($A7,Данные!$A$2:$O$11,14,0), VLOOKUP($A7,Данные!$A$2:$O$11,15,0) ) -> 17.559423 | E7: =IF(C7=0,0,(D7/C7*100)) -> 33.44652 | F7: =IF(E7<=10,"X",IF(E7<=25,"Y","Z")) -> Z | G7: =IF(F7="X","✅ Стабильный спрос - точный прогноз", IF(F7="Y","⚠️ Умеренные колебания - корректировать заказ", "❌ Нестабильность - под заказ")) -> ❌ Нестабильность - под заказ
A8: =Данные[Sku] -> SKU007 | B8: =Данные[Товар] -> Холод Pro | C8: =AVERAGE(Данные!L8:O8) -> 26 | D8: =_xlfn.STDEV.S( VLOOKUP($A8,Данные!$A$2:$O$11,12,0), VLOOKUP($A8,Данные!$A$2:$O$11,13,0), VLOOKUP($A8,Данные!$A$2:$O$11,14,0), VLOOKUP($A8,Данные!$A$2:$O$11,15,0) ) -> 3.6514837 | E8: =IF(C8=0,0,(D8/C8*100)) -> 14.044168 | F8: =IF(E8<=10,"X",IF(E8<=25,"Y","Z")) -> Y | G8: =IF(F8="X","✅ Стабильный спрос - точный прогноз", IF(F8="Y","⚠️ Умеренные колебания - корректировать заказ", "❌ Нестабильность - под заказ")) -> ⚠️ Умеренные колебания - корректировать заказ
A9: =Данные[Sku] -> SKU008 | B9: =Данные[Товар] -> Стиралка Slim | C9: =AVERAGE(Данные!L9:O9) -> 47.75 | D9: =_xlfn.STDEV.S( VLOOKUP($A9,Данные!$A$2:$O$11,12,0), VLOOKUP($A9,Данные!$A$2:$O$11,13,0), VLOOKUP($A9,Данные!$A$2:$O$11,14,0), VLOOKUP($A9,Данные!$A$2:$O$11,15,0) ) -> 4.1932485 | E9: =IF(C9=0,0,(D9/C9*100)) -> 8.7816723 | F9: =IF(E9<=10,"X",IF(E9<=25,"Y","Z")) -> X | G9: =IF(F9="X","✅ Стабильный спрос - точный прогноз", IF(F9="Y","⚠️ Умеренные колебания - корректировать заказ", "❌ Нестабильность - под заказ")) -> ✅ Стабильный спрос - точный прогноз
A10: =Данные[Sku] -> SKU009 | B10: =Данные[Товар] -> Микра Smart | C10: =AVERAGE(Данные!L10:O10) -> 66 | D10: =_xlfn.STDEV.S( VLOOKUP($A10,Данные!$A$2:$O$11,12,0), VLOOKUP($A10,Данные!$A$2:$O$11,13,0), VLOOKUP($A10,Данные!$A$2:$O$11,14,0), VLOOKUP($A10,Данные!$A$2:$O$11,15,0) ) -> 8.8317609 | E10: =IF(C10=0,0,(D10/C10*100)) -> 13.381456 | F10: =IF(E10<=10,"X",IF(E10<=25,"Y","Z")) -> Y | G10: =IF(F10="X","✅ Стабильный спрос - точный прогноз", IF(F10="Y","⚠️ Умеренные колебания - корректировать заказ", "❌ Нестабильность - под заказ")) -> ⚠️ Умеренные колебания - корректировать заказ
A11: =Данные[Sku] -> SKU010 | B11: =Данные[Товар] -> Чайник Styline | C11: =AVERAGE(Данные!L11:O11) -> 86.75 | D11: =_xlfn.STDEV.S( VLOOKUP($A11,Данные!$A$2:$O$11,12,0), VLOOKUP($A11,Данные!$A$2:$O$11,13,0), VLOOKUP($A11,Данные!$A$2:$O$11,14,0), VLOOKUP($A11,Данные!$A$2:$O$11,15,0) ) -> 6.9940451 | E11: =IF(C11=0,0,(D11/C11*100)) -> 8.0622998 | F11: =IF(E11<=10,"X",IF(E11<=25,"Y","Z")) -> X | G11: =IF(F11="X","✅ Стабильный спрос - точный прогноз", IF(F11="Y","⚠️ Умеренные колебания - корректировать заказ", "❌ Нестабильность - под заказ")) -> ✅ Стабильный спрос - точный прогноз

Sheet Запасы_и_заказы
A1: Sku | B1: Товар | C1: Запасы | D1: Продажи/мес | E1: Цена | F1: Дней запаса | G1: Оборач. | H1: Рекомендация | I1: Заказ (шт) | J1: Сумма заказа
A2: =Данные[Sku] -> SKU001 | B2: =Данные[Товар] -> Холодильник F | C2: =VLOOKUP($A2,Данные!$A$2:$O$11,11,0) -> 20 | D2: =VLOOKUP($A2,Данные!$A$2:$O$11,7,0) -> 120 | E2: =VLOOKUP($A2,Данные!$A$2:$O$11,5,0) -> 30000 | F2: =IF(D2=0,999,ROUND(C2/(D2/30),0)) -> 5 | G2: =IF(D2=0,0,ROUND(30/(D2/30),1)) -> 7.5 | H2: =IF(F2<=14,"🔴 СРОЧНЫЙ ЗАКАЗ", IF(F2<=30,"🟡 ПЛАНИРОВАТЬ ЗАКАЗ", IF(F2<=60,"🟢 ЗАПАС В НОРМЕ", IF(F2<=90,"⚠️ ПРОВЕРИТЬ СПРОС", "❌ ИЗЛИШЕК - СКИДКА")))) -> 🔴 СРОЧНЫЙ ЗАКАЗ | I2: =IF(H2="🔴 СРОЧНЫЙ ЗАКАЗ",MAX(0,ROUNDUP(D2*1.5,0)-C2), IF(H2="🟡 ПЛАНИРОВАТЬ ЗАКАЗ",MAX(0,ROUNDUP(D2*1.5,0)-C2),0)) -> 160 | J2: =I2*E2 -> 4800000
A3: =Данные[Sku] -> SKU002 | B3: =Данные[Товар] -> Холодильник B | C3: =VLOOKUP($A3,Данные!$A$2:$O$11,11,0) -> 30 | D3: =VLOOKUP($A3,Данные!$A$2:$O$11,7,0) -> 60 | E3: =VLOOKUP($A3,Данные!$A$2:$O$11,5,0) -> 35000 | F3: =IF(D3=0,999,ROUND(C3/(D3/30),0)) -> 15 | G3: =IF(D3=0,0,ROUND(30/(D3/30),1)) -> 15 | H3: =IF(F3<=14,"🔴 СРОЧНЫЙ ЗАКАЗ", IF(F3<=30,"🟡 ПЛАНИРОВАТЬ ЗАКАЗ", IF(F3<=60,"🟢 ЗАПАС В НОРМЕ", IF(F3<=90,"⚠️ ПРОВЕРИТЬ СПРОС", "❌ ИЗЛИШЕК - СКИДКА")))) -> 🟡 ПЛАНИРОВАТЬ ЗАКАЗ | I3: =IF(H3="🔴 СРОЧНЫЙ ЗАКАЗ",MAX(0,ROUNDUP(D3*1.5,0)-C3), IF(H3="🟡 ПЛАНИРОВАТЬ ЗАКАЗ",MAX(0,ROUNDUP(D3*1.5,0)-C3),0)) -> 60 | J3: =I3*E3 -> 2100000
A4: =Данные[Sku] -> SKU003 | B4: =Данные[Товар] -> Стиралка C | C4: =VLOOKUP($A4,Данные!$A$2:$O$11,11,0) -> 10 | D4: =VLOOKUP($A4,Данные!$A$2:$O$11,7,0) -> 80 | E4: =VLOOKUP($A4,Данные!$A$2:$O$11,5,0) -> 45000 | F4: =IF(D4=0,999,ROUND(C4/(D4/30),0)) -> 4 | G4: =IF(D4=0,0,ROUND(30/(D4/30),1)) -> 11.3 | H4: =IF(F4<=14,"🔴 СРОЧНЫЙ ЗАКАЗ", IF(F4<=30,"🟡 ПЛАНИРОВАТЬ ЗАКАЗ", IF(F4<=60,"🟢 ЗАПАС В НОРМЕ", IF(F4<=90,"⚠️ ПРОВЕРИТЬ СПРОС", "❌ ИЗЛИШЕК - СКИДКА")))) -> 🔴 СРОЧНЫЙ ЗАКАЗ | I4: =IF(H4="🔴 СРОЧНЫЙ ЗАКАЗ",MAX(0,ROUNDUP(D4*1.5,0)-C4), IF(H4="🟡 ПЛАНИРОВАТЬ ЗАКАЗ",MAX(0,ROUNDUP(D4*1.5,0)-C4),0)) -> 110 | J4: =I4*E4 -> 4950000
A5: =Данные[Sku] -> SKU004 | B5: =Данные[Товар] -> Микра D | C5: =VLOOKUP($A5,Данные!$A$2:$O$11,11,0) -> 50 | D5: =VLOOKUP($A5,Данные!$A$2:$O$11,7,0) -> 150 | E5: =VLOOKUP($A5,Данные!$A$2:$O$11,5,0) -> 8000 | F5: =IF(D5=0,999,ROUND(C5/(D5/30),0)) -> 10 | G5: =IF(D5=0,0,ROUND(30/(D5/30),1)) -> 6 | H5: =IF(F5<=14,"🔴 СРОЧНЫЙ ЗАКАЗ", IF(F5<=30,"🟡 ПЛАНИРОВАТЬ ЗАКАЗ", IF(F5<=60,"🟢 ЗАПАС В НОРМЕ", IF(F5<=90,"⚠️ ПРОВЕРИТЬ СПРОС", "❌ ИЗЛИШЕК - СКИДКА")))) -> 🔴 СРОЧНЫЙ ЗАКАЗ | I5: =IF(H5="🔴 СРОЧНЫЙ ЗАКАЗ",MAX(0,ROUNDUP(D5*1.5,0)-C5), IF(H5="🟡 ПЛАНИРОВАТЬ ЗАКАЗ",MAX(0,ROUNDUP(D5*1.5,0)-C5),0)) -> 175 | J5: =I5*E5 -> 1400000
A6: =Данные[Sku] -> SKU005 | B6: =Данные[Товар] -> Чайник E | C6: =VLOOKUP($A6,Данные!$A$2:$O$11,11,0) -> 200 | D6: =VLOOKUP($A6,Данные!$A$2:$O$11,7,0) -> 300 | E6: =VLOOKUP($A6,Данные!$A$2:$O$11,5,0) -> 2500 | F6: =IF(D6=0,999,ROUND(C6/(D6/30),0)) -> 20 | G6: =IF(D6=0,0,ROUND(30/(D6/30),1)) -> 3 | H6: =IF(F6<=14,"🔴 СРОЧНЫЙ ЗАКАЗ", IF(F6<=30,"🟡 ПЛАНИРОВАТЬ ЗАКАЗ", IF(F6<=60,"🟢 ЗАПАС В НОРМЕ", IF(F6<=90,"⚠️ ПРОВЕРИТЬ СПРОС", "❌ ИЗЛИШЕК - СКИДКА")))) -> 🟡 ПЛАНИРОВАТЬ ЗАКАЗ | I6: =IF(H6="🔴 СРОЧНЫЙ ЗАКАЗ",MAX(0,ROUNDUP(D6*1.5,0)-C6), IF(H6="🟡 ПЛАНИРОВАТЬ ЗАКАЗ",MAX(0,ROUNDUP(D6*1.5,0)-C6),0)) -> 250 | J6: =I6*E6 -> 625000
A7: =Данные[Sku] -> SKU006 | B7: =Данные[Товар] -> Чайник F | C7: =VLOOKUP($A7,Данные!$A$2:$O$11,11,0) -> 40 | D7: =VLOOKUP($A7,Данные!$A$2:$O$11,7,0) -> 50 | E7: =VLOOKUP($A7,Данные!$A$2:$O$11,5,0) -> 2000 | F7: =IF(D7=0,999,ROUND(C7/(D7/30),0)) -> 24 | G7: =IF(D7=0,0,ROUND(30/(D7/30),1)) -> 18 | H7: =IF(F7<=14,"🔴 СРОЧНЫЙ ЗАКАЗ", IF(F7<=30,"🟡 ПЛАНИРОВАТЬ ЗАКАЗ", IF(F7<=60,"🟢 ЗАПАС В НОРМЕ", IF(F7<=90,"⚠️ ПРОВЕРИТЬ СПРОС", "❌ ИЗЛИШЕК - СКИДКА")))) -> 🟡 ПЛАНИРОВАТЬ ЗАКАЗ | I7: =IF(H7="🔴 СРОЧНЫЙ ЗАКАЗ",MAX(0,ROUNDUP(D7*1.5,0)-C7), IF(H7="🟡 ПЛАНИРОВАТЬ ЗАКАЗ",MAX(0,ROUNDUP(D7*1.5,0)-C7),0)) -> 35 | J7: =I7*E7 -> 70000
A8: =Данные[Sku] -> SKU007 | B8: =Данные[Товар] -> Холод Pro | C8: =VLOOKUP($A8,Данные!$A$2:$O$11,11,0) -> 8 | D8: =VLOOKUP($A8,Данные!$A$2:$O$11,7,0) -> 25 | E8: =VLOOKUP($A8,Данные!$A$2:$O$11,5,0) -> 55000 | F8: =IF(D8=0,999,ROUND(C8/(D8/30),0)) -> 10 | G8: =IF(D8=0,0,ROUND(30/(D8/30),1)) -> 36 | H8: =IF(F8<=14,"🔴 СРОЧНЫЙ ЗАКАЗ", IF(F8<=30,"🟡 ПЛАНИРОВАТЬ ЗАКАЗ", IF(F8<=60,"🟢 ЗАПАС В НОРМЕ", IF(F8<=90,"⚠️ ПРОВЕРИТЬ СПРОС", "❌ ИЗЛИШЕК - СКИДКА")))) -> 🔴 СРОЧНЫЙ ЗАКАЗ | I8: =IF(H8="🔴 СРОЧНЫЙ ЗАКАЗ",MAX(0,ROUNDUP(D8*1.5,0)-C8), IF(H8="🟡 ПЛАНИРОВАТЬ ЗАКАЗ",MAX(0,ROUNDUP(D8*1.5,0)-C8),0)) -> 30 | J8: =I8*E8 -> 1650000
A9: =Данные[Sku] -> SKU008 | B9: =Данные[Товар] -> Стиралка Slim | C9: =VLOOKUP($A9,Данные!$A$2:$O$11,11,0) -> 15 | D9: =VLOOKUP($A9,Данные!$A$2:$O$11,7,0) -> 45 | E9: =VLOOKUP($A9,Данные!$A$2:$O$11,5,0) -> 32000 | F9: =IF(D9=0,999,ROUND(C9/(D9/30),0)) -> 10 | G9: =IF(D9=0,0,ROUND(30/(D9/30),1)) -> 20 | H9: =IF(F9<=14,"🔴 СРОЧНЫЙ ЗАКАЗ", IF(F9<=30,"🟡 ПЛАНИРОВАТЬ ЗАКАЗ", IF(F9<=60,"🟢 ЗАПАС В НОРМЕ", IF(F9<=90,"⚠️ ПРОВЕРИТЬ СПРОС", "❌ ИЗЛИШЕК - СКИДКА")))) -> 🔴 СРОЧНЫЙ ЗАКАЗ | I9: =IF(H9="🔴 СРОЧНЫЙ ЗАКАЗ",MAX(0,ROUNDUP(D9*1.5,0)-C9), IF(H9="🟡 ПЛАНИРОВАТЬ ЗАКАЗ",MAX(0,ROUNDUP(D9*1.5,0)-C9),0)) -> 53 | J9: =I9*E9 -> 1696000
A10: =Данные[Sku] -> SKU009 | B10: =Данные[Товар] -> Микра Smart | C10: =VLOOKUP($A10,Данные!$A$2:$O$11,11,0) -> 22 | D10: =VLOOKUP($A10,Данные!$A$2:$O$11,7,0) -> 65 | E10: =VLOOKUP($A10,Данные!$A$2:$O$11,5,0) -> 12000 | F10: =IF(D10=0,999,ROUND(C10/(D10/30),0)) -> 10 | G10: =IF(D10=0,0,ROUND(30/(D10/30),1)) -> 13.8 | H10: =IF(F10<=14,"🔴 СРОЧНЫЙ ЗАКАЗ", IF(F10<=30,"🟡 ПЛАНИРОВАТЬ ЗАКАЗ", IF(F10<=60,"🟢 ЗАПАС В НОРМЕ", IF(F10<=90,"⚠️ ПРОВЕРИТЬ СПРОС", "❌ ИЗЛИШЕК - СКИДКА")))) -> 🔴 СРОЧНЫЙ ЗАКАЗ | I10: =IF(H10="🔴 СРОЧНЫЙ ЗАКАЗ",MAX(0,ROUNDUP(D10*1.5,0)-C10), IF(H10="🟡 ПЛАНИРОВАТЬ ЗАКАЗ",MAX(0,ROUNDUP(D10*1.5,0)-C10),0)) -> 76 | J10: =I10*E10 -> 912000
A11: =Данные[Sku] -> SKU010 | B11: =Данные[Товар] -> Чайник Styline | C11: =VLOOKUP($A11,Данные!$A$2:$O$11,11,0) -> 65 | D11: =VLOOKUP($A11,Данные!$A$2:$O$11,7,0) -> 85 | E11: =VLOOKUP($A11,Данные!$A$2:$O$11,5,0) -> 3200 | F11: =IF(D11=0,999,ROUND(C11/(D11/30),0)) -> 23 | G11: =IF(D11=0,0,ROUND(30/(D11/30),1)) -> 10.6 | H11: =IF(F11<=14,"🔴 СРОЧНЫЙ ЗАКАЗ", IF(F11<=30,"🟡 ПЛАНИРОВАТЬ ЗАКАЗ", IF(F11<=60,"🟢 ЗАПАС В НОРМЕ", IF(F11<=90,"⚠️ ПРОВЕРИТЬ СПРОС", "❌ ИЗЛИШЕК - СКИДКА")))) -> 🟡 ПЛАНИРОВАТЬ ЗАКАЗ | I11: =IF(H11="🔴 СРОЧНЫЙ ЗАКАЗ",MAX(0,ROUNDUP(D11*1.5,0)-C11), IF(H11="🟡 ПЛАНИРОВАТЬ ЗАКАЗ",MAX(0,ROUNDUP(D11*1.5,0)-C11),0)) -> 63 | J11: =I11*E11 -> 201600
C15: 📊 ДАШБОРД УПРАВЛЕНИЯ ЗАПАСАМИ
C17: КРИТИЧНО | D17: =COUNTIF(H2:H11,"🔴*") & " товаров" -> 6 товаров | E17: На сумму: | F17: ="₽ " & TEXT(SUMIF(H2:H11,"🔴*",J2:J11),"# ##0") -> ₽ 15 408 000
C18: В ПЛАНЕ | D18: =COUNTIF(H2:H11,"🟡*") & " товаров" -> 4 товаров | E18: На сумму: | F18: ="₽ " & TEXT(SUMIF(H2:H11,"🟡*",J2:J11),"# ##0") -> ₽ 2 996 600
C20: "💰 ИТОГО К ЗАКАЗУ:" | E20: =SUM(I2:I11) & " шт" -> 1012 шт | F20: ="на ₽ " & TEXT(SUM(J2:J11),"# ##0") -> на ₽ 18 404 600
